7 Segment Display/bin_7seg_disp_rtl.v
`timescale 1ns/1ns
// Nicholas Saylor 10/14/2021
// CMPEN 270 Verilog Project 6
// This is the module for the 7 segment display
//---        ---   ---         ---  ---  ---   ---   ---  ---       ---         ---   ---
//| |    |     |     |   | |   |    |      |   | |   | |  | |  |    |       |   |     |
//           ---   ---   ---   ---  ---        ---   ---  ---  ---        ---   ---   ---
//| |    |   |       |     |     |  | |    |   | |     |  | |  | |  |     | |   |     |
//---        ---   ---         ---  ---        ---             ---  ---   ---   ---

module bin_7seg_disp_rtl(MODE, DATA, a, b, c, d, e, f, g, dp);
    input MODE; // 0 for binary, 1 for 2s complement
    input [3:0] DATA; // 4 bit input
    output reg a, b, c, d, e, f, g; // Segments
    output reg dp; // Decimal point for 2s complement

    always @ (MODE or DATA)
    begin
        //Case statement containing all possible values for DATA
        case(DATA)
            4'b0000:
            begin
                a = 0;
                b = 0;
                c = 0;
                d = 0;
                e = 0;
                f = 0;
                g = 0;
                dp = 1;
                //---
                //| |
                //
                //| |
                //---
            end
            4'b0001:
            begin
                a = 1;
                b = 0;
                c = 0;
                d = 1;
                e=1;
                f=1;
                g=1;
                dp = 1;
                //
                //  |
                //
                //  |
                //
            end
            4'b0010:
            begin
                a=0;
                b=0;
                c=1;
                d=0;
                e=0;
                f=0;
                g=1;
                dp = 1;
                //---
                //  |
                //---
                //|
                //---
            end
            4'b0011:
            begin
                a=0;
                b=0;
                c=0;
                d=0;
                e=1;
                f=1;
                g=0;
                dp=1;
                //---
                //  |
                //---
                //  |
                //---
            end
            4'b0100:
            begin
                a=1;
                b=0;
                c=0;
                d=1;
                e=1;
                f=0;
                g=0;
                dp=1;
                //
                //| |
                //---
                //  |
                //
            end
            4'b0101:
            begin
                a=0;
                b=1;
                c=0;
                d=0;
                e=1;
                f=0;
                g=0;
                dp=1;
                //---
                //|
                //---
                //  |
                //---
            end
            4'b0110:
            begin
                a=0;
                b=1;
                c=0;
                d=0;
                e=0;
                f=0;
                g=0;
                dp=1;
                //---
                //|
                //---
                //| |
                //---
            end
            4'b0111:
            begin
                a=0;
                b=0;
                c=0;
                d=1;
                e=1;
                f=1;
                g=1;
                dp=1;
                //---
                //  |
                //
                //  |
                //
            end
            4'b1000:
            if (MODE)
                begin
                    a=0;
                    b=0;
                    c=0;
                    d=0;
                    e=0;
                    f=0;
                    g=0;
                    dp=0;
                    //---
                    //| |
                    //---
                    //| |
                    //---.
                end
            else
                begin
                    a=0;
                    b=0;
                    c=0;
                    d=0;
                    e=0;
                    f=0;
                    g=0;
                    dp=1;
                    //---
                    //| |
                    //---
                    //| |
                    //---
                end
            4'b1001:
            if (MODE)
                begin
                    a=0;
                    b=0;
                    c=0;
                    d=1;
                    e=1;
                    f=1;
                    g=1;
                    dp=0;
                    //---
                    //  |
                    //
                    //  |
                    //   .
                end
            else
                begin
                    a=0;
                    b=0;
                    c=0;
                    d=1;
                    e=1;
                    f=0;
                    g=0;
                    dp=1;
                    //---
                    //| |
                    //---
                    //  |
                    //
                end
            4'b1010:
            if (MODE)
                begin
                    a=0;
                    b=1;
                    c=0;
                    d=0;
                    e=0;
                    f=0;
                    g=0;
                    dp=0;
                    //---
                    //|
                    //---
                    //| |
                    //---.
                end
            else
                begin
                    a=0;
                    b=0;
                    c=0;
                    d=1;
                    e=0;
                    f=0;
                    g=0;
                    dp=1;
                    //---
                    //| |
                    //---
                    //| |
                    //
                end
            4'b1011:
            if (MODE)
                begin
                    a=0;
                    b=1;
                    c=0;
                    d=0;
                    e=1;
                    f=0;
                    g=0;
                    dp=0;
                    //---
                    //|
                    //---
                    //  |
                    //---.
                end
            else
                begin
                    a=1;
                    b=1;
                    c=0;
                    d=0;
                    e=0;
                    f=0;
                    g=0;
                    dp=1;
                    //
                    //|
                    //---
                    //| |
                    //---
                end
            4'b1100:
            if (MODE)
                begin
                    a=1;
                    b=0;
                    c=0;
                    d=1;
                    e=1;
                    f=0;
                    g=0;
                    dp=0;
                    //
                    //| |
                    //---
                    //  |
                    //   .
                end
            else
                begin
                    a=0;
                    b=1;
                    c=1;
                    d=0;
                    e=0;
                    f=0;
                    g=1;
                    dp=1;
                    //---
                    //|
                    //
                    //|
                    //---
                end
            4'b1101:
            if (MODE)
                begin
                    a=0;
                    b=0;
                    c=0;
                    d=0;
                    e=1;
                    f=1;
                    g=0;
                    dp=0;
                    //---
                    //  |
                    //---
                    //  |
                    //---.
                end
            else
                begin
                    a=1;
                    b=0;
                    c=0;
                    d=0;
                    e=0;
                    f=1;
                    g=0;
                    dp=1;
                    //
                    //  |
                    //---
                    //| |
                    //---
                end
            4'b1110:
            if (MODE)
                begin
                    a=0;
                    b=0;
                    c=1;
                    d=0;
                    e=0;
                    f=0;
                    g=1;
                    dp = 0;
                    //---
                    //  |
                    //---
                    //|
                    //---.
                end
            else
                begin
                    a=0;
                    b=1;
                    c=1;
                    d=0;
                    e=0;
                    f=0;
                    g=0;
                    dp=1;
                    //---
                    //|
                    //---
                    //|
                    //---
                end
            4'b1111:
            if (MODE)
                begin
                    a=1;
                    b=0;
                    c=0;
                    d=1;
                    e=1;
                    f=1;
                    g=1;
                    dp=0;
                    //
                    //  |
                    //
                    //  |
                    //   .
                end
            else
                begin
                    a=0;
                    b=1;
                    c=1;
                    d=1;
                    e=0;
                    f=0;
                    g=0;
                    dp=1;
                    //---
                    //|
                    //---
                    //|
                    //
                end
        endcase
    end

endmodule

7 Segment Display/bin_7seg_disp_test.v
`timescale 1ns/1ns

module bin_7seg_disp_test();
    reg [4:0] count = 0; // Tracks iterations (5 inputs)
    wire [7:0] z; // RTL output
    
    
    always begin
        #100 count = count + 1; // Iterates through truth table
        if (&count) #100 $finish; // Avoid overflow
    end
    
    initial begin
        $dumpfile("./bin_7seg_disp.vcd"); // Output vcd file
        $dumpvars;
        // Titles
        $display("%4s     %5s     %5s     %5s     %5s     %1s     %1s     %1s     %1s     %1s     %1s     %1s     %2s",
        "MODE", "DATA3", "DATA2", "DATA1", "DATA0", "A", "B", "C", "D", "E", "F", "G", "DP");
    end
    
    always @(count) begin
        #90 $strobe("%4d     %5d     %5d     %5d     %5d     %1d     %1d     %1d     %1d     %1d     %1d     %1d     %2d",
        count[4], count[3], count[2], count[1], count[0], z[7], z[6], z[5], z[4], z[3], z[2], z[1], z[0]);
    end


    // RTL model
    bin_7seg_disp_rtl c1 (.MODE(count[4]), .DATA(count[3:0]), .a(z[7]), .b(z[6]), .c(z[5]), .d(z[4]), .e(z[3]), .f(z[2]), .g(z[1]), .dp(z[0]));


endmodule

7 Segment Display/bin_7seg_disp.vcd
$date
	Thu Oct 14 23:19:16 2021
$end
$version
	Icarus Verilog
$end
$timescale
	1ns
$end
$scope module bin_7seg_disp_test $end
$var wire 8 ! z [7:0] $end
$var reg 5 " count [4:0] $end
$scope module c1 $end
$var wire 4 # DATA [3:0] $end
$var wire 1 $ MODE $end
$var reg 1 % a $end
$var reg 1 & b $end
$var reg 1 ' c $end
$var reg 1 ( d $end
$var reg 1 ) dp $end
$var reg 1 * e $end
$var reg 1 + f $end
$var reg 1 , g $end
$upscope $end
$upscope $end
$enddefinitions $end
#0
$dumpvars
0,
0+
0*
1)
0(
0'
0&
0%
0$
b0 #
b0 "
b1 !
$end
#100
1,
1+
1*
1(
1%
b10011111 !
b1 #
b1 "
#200
0+
0*
0(
1'
0%
b100011 !
b10 #
b10 "
#300
0,
1+
1*
0'
b1101 !
b11 #
b11 "
#400
0+
1(
1%
b10011001 !
b100 #
b100 "
#500
0(
1&
0%
b1001001 !
b101 #
b101 "
#600
0*
b1000001 !
b110 #
b110 "
#700
1,
1+
1*
1(
0&
b11111 !
b111 #
b111 "
#800
0,
0+
0*
0(
b1 !
b1000 #
b1000 "
#900
1*
1(
b11001 !
b1001 #
b1001 "
#1000
0*
b10001 !
b1010 #
b1010 "
#1100
0(
1&
1%
b11000001 !
b1011 #
b1011 "
#1200
1,
1'
0%
b1100011 !
b1100 #
b1100 "
#1300
0,
1+
0'
0&
1%
b10000101 !
b1101 #
b1101 "
#1400
0+
1'
1&
0%
b1100001 !
b1110 #
b1110 "
#1500
1(
b1110001 !
b1111 #
b1111 "
#1600
0(
0'
0&
b1 !
1$
b0 #
b10000 "
#1700
1,
1+
1*
1(
1%
b10011111 !
b1 #
b10001 "
#1800
0+
0*
0(
1'
0%
b100011 !
b10 #
b10010 "
#1900
0,
1+
1*
0'
b1101 !
b11 #
b10011 "
#2000
0+
1(
1%
b10011001 !
b100 #
b10100 "
#2100
0(
1&
0%
b1001001 !
b101 #
b10101 "
#2200
0*
b1000001 !
b110 #
b10110 "
#2300
1,
1+
1*
1(
0&
b11111 !
b111 #
b10111 "
#2400
0)
0,
0+
0*
0(
b0 !
b1000 #
b11000 "
#2500
1,
1+
1*
1(
b11110 !
b1001 #
b11001 "
#2600
0,
0+
0*
0(
1&
b1000000 !
b1010 #
b11010 "
#2700
1*
b1001000 !
b1011 #
b11011 "
#2800
1(
0&
1%
b10011000 !
b1100 #
b11100 "
#2900
1+
0(
0%
b1100 !
b1101 #
b11101 "
#3000
1,
0+
0*
1'
b100010 !
b1110 #
b11110 "
#3100
1+
1*
1(
0'
1%
b10011110 !
b1111 #
b11111 "
